pargeo/__init__.py
pargeo/constraint.py
pargeo/domain.py
pargeo/geometry.py
pargeo/transform.py
pargeo/utils/constants.py
pargeo/utils/geometry_utils.py
pargeo/utils/gmsh_utils.py
pargeo/utils/plot_utils.py
pargeo/utils/typing_utils.py
pargeo-0.3.4.dist-info/LICENSE
pargeo-0.3.4.dist-info/METADATA
pargeo-0.3.4.dist-info/WHEEL
pargeo-0.3.4.dist-info/RECORD
